LICENSE
README.md
setup.py
pygameGL/__init__.py
pygameGL/sogl.py
pygameGL/swarm.py
pygameGL/assets/pygameGL.aseprite
pygameGL/assets/pygameGL.ico
pygameGL/assets/pygameGL.png
pygameGL/assets/pygameGL_500x.png
pygameGL/audio/__init__.py
pygameGL/draw/__init__.py
pygameGL/event/__init__.py
pygameGL/ext/SoGL/glew32.dll
pygameGL/ext/SoGL/glfw3.dll
pygameGL/ext/SoGL/sogl64.dll
pygameGL_devex.egg-info/PKG-INFO
pygameGL_devex.egg-info/SOURCES.txt
pygameGL_devex.egg-info/dependency_links.txt
pygameGL_devex.egg-info/requires.txt
pygameGL_devex.egg-info/top_level.txt